compdescriptors.py
compdescriptors-0.1.0.dist-info/METADATA
compdescriptors-0.1.0.dist-info/RECORD
compdescriptors-0.1.0.dist-info/WHEEL
compdescriptors-0.1.0.dist-info/top_level.txt
